{"id":"e2554796-c866-430a-a56d-609b758bbcfb","revision":0,"last_node_id":111,"last_link_id":333,"nodes":[{"id":22,"type":"BasicGuider","pos":[278,37],"size":[222.3482666015625,46],"flags":{},"order":13,"mode":0,"inputs":[{"localized_name":"model","name":"model","type":"MODEL","link":332},{"localized_name":"conditioning","name":"conditioning","type":"CONDITIONING","link":42}],"outputs":[{"localized_name":"GUIDER","name":"GUIDER","shape":3,"type":"GUIDER","slot_index":0,"links":[30]}],"properties":{"cnr_id":"comfy-core","ver":"0.3.27","Node name for S&R":"BasicGuider"},"widgets_values":[]},{"id":27,"type":"EmptySD3LatentImage","pos":[-99,138],"size":[315,106],"flags":{},"order":0,"mode":0,"inputs":[],"outputs":[{"localized_name":"LATENT","name":"LATENT","shape":3,"type":"LATENT","slot_index":0,"links":[116]}],"properties":{"cnr_id":"comfy-core","ver":"0.3.27","Node name for S&R":"EmptySD3LatentImage"},"widgets_values":[896,1152,1]},{"id":8,"type":"VAEDecode","pos":[270,125],"size":[210,46],"flags":{},"order":15,"mode":0,"inputs":[{"localized_name":"samples","name":"samples","type":"LATENT","link":24},{"localized_name":"vae","name":"vae","type":"VAE","link":12}],"outputs":[{"localized_name":"IMAGE","name":"IMAGE","type":"IMAGE","slot_index":0,"links":[233]}],"properties":{"cnr_id":"comfy-core","ver":"0.3.27","Node name for S&R":"VAEDecode"},"widgets_values":[]},{"id":6,"type":"CLIPTextEncode","pos":[-90.753662109375,733.95263671875],"size":[285.6000061035156,58],"flags":{"collapsed":false},"order":10,"mode":0,"inputs":[{"localized_name":"clip","name":"clip","type":"CLIP","link":230},{"name":"text","type":"STRING","widget":{"name":"text"},"link":138}],"outputs":[{"localized_name":"CONDITIONING","name":"CONDITIONING","type":"CONDITIONING","slot_index":0,"links":[41]}],"title":"CLIP Text Encode (Positive Prompt)","properties":{"cnr_id":"comfy-core","ver":"0.3.27","Node name for S&R":"CLIPTextEncode"},"widgets_values":["a beautiful red-haired woman with white skin posing nude standing on the beatch show his hands with splashing ocean water and sunset in the distance,face cam"],"color":"#232","bgcolor":"#353"},{"id":16,"type":"KSamplerSelect","pos":[416.1782531738281,915.6884155273438],"size":[315,58],"flags":{},"order":1,"mode":0,"inputs":[],"outputs":[{"localized_name":"SAMPLER","name":"SAMPLER","shape":3,"type":"SAMPLER","links":[19]}],"properties":{"cnr_id":"comfy-core","ver":"0.3.27","Node name for S&R":"KSamplerSelect"},"widgets_values":["euler"]},{"id":26,"type":"FluxGuidance","pos":[-84,31],"size":[317.4000244140625,58],"flags":{},"order":12,"mode":0,"inputs":[{"localized_name":"conditioning","name":"conditioning","type":"CONDITIONING","link":41}],"outputs":[{"localized_name":"CONDITIONING","name":"CONDITIONING","shape":3,"type":"CONDITIONING","slot_index":0,"links":[42]}],"properties":{"cnr_id":"comfy-core","ver":"0.3.27","Node name for S&R":"FluxGuidance"},"widgets_values":[3],"color":"#233","bgcolor":"#355"},{"id":11,"type":"DualCLIPLoader","pos":[-115.41547393798828,297.9347229003906],"size":[348.4336242675781,122],"flags":{},"order":2,"mode":0,"inputs":[],"outputs":[{"localized_name":"CLIP","name":"CLIP","shape":3,"type":"CLIP","slot_index":0,"links":[230]}],"properties":{"cnr_id":"comfy-core","ver":"0.3.27","Node name for S&R":"DualCLIPLoader"},"widgets_values":["t5xxl_fp16.safetensors","clip_l.safetensors","flux","default"]},{"id":13,"type":"SamplerCustomAdvanced","pos":[597.287353515625,35.11071014404297],"size":[277.20001220703125,124.53733825683594],"flags":{},"order":14,"mode":0,"inputs":[{"localized_name":"noise","name":"noise","type":"NOISE","link":37},{"localized_name":"guider","name":"guider","type":"GUIDER","link":30},{"localized_name":"sampler","name":"sampler","type":"SAMPLER","link":19},{"localized_name":"sigmas","name":"sigmas","type":"SIGMAS","link":20},{"localized_name":"latent_image","name":"latent_image","type":"LATENT","link":116}],"outputs":[{"localized_name":"output","name":"output","shape":3,"type":"LATENT","slot_index":0,"links":[24]},{"localized_name":"denoised_output","name":"denoised_output","shape":3,"type":"LATENT","links":null}],"properties":{"cnr_id":"comfy-core","ver":"0.3.27","Node name for S&R":"SamplerCustomAdvanced"},"widgets_values":[]},{"id":10,"type":"VAELoader","pos":[-108.3852310180664,472.71539306640625],"size":[311.81634521484375,60.429901123046875],"flags":{},"order":3,"mode":0,"inputs":[],"outputs":[{"localized_name":"VAE","name":"VAE","shape":3,"type":"VAE","slot_index":0,"links":[12]}],"properties":{"cnr_id":"comfy-core","ver":"0.3.27","Node name for S&R":"VAELoader"},"widgets_values":["ae.sft"]},{"id":25,"type":"RandomNoise","pos":[413.0743103027344,787.1038208007812],"size":[315,82],"flags":{},"order":4,"mode":0,"inputs":[],"outputs":[{"localized_name":"NOISE","name":"NOISE","shape":3,"type":"NOISE","links":[37]}],"properties":{"cnr_id":"comfy-core","ver":"0.3.27","Node name for S&R":"RandomNoise"},"widgets_values":[720566940214131,"randomize"],"color":"#2a363b","bgcolor":"#3f5159"},{"id":12,"type":"UNETLoader","pos":[-123.07730102539062,571.4569702148438],"size":[315,82],"flags":{},"order":5,"mode":0,"inputs":[],"outputs":[{"localized_name":"MODEL","name":"MODEL","shape":3,"type":"MODEL","slot_index":0,"links":[331]}],"properties":{"cnr_id":"comfy-core","ver":"0.3.27","Node name for S&R":"UNETLoader"},"widgets_values":["CreArt_Ultimate.safetensors","fp8_e4m3fn"],"color":"#223","bgcolor":"#335"},{"id":17,"type":"BasicScheduler","pos":[426.42364501953125,1021.0136108398438],"size":[315,106],"flags":{},"order":9,"mode":0,"inputs":[{"localized_name":"model","name":"model","type":"MODEL","link":333}],"outputs":[{"localized_name":"SIGMAS","name":"SIGMAS","shape":3,"type":"SIGMAS","links":[20]}],"properties":{"cnr_id":"comfy-core","ver":"0.3.27","Node name for S&R":"BasicScheduler"},"widgets_values":["beta",10,1]},{"id":48,"type":"CreaPrompt List","pos":[258.1661071777344,215.57540893554688],"size":[431.5010070800781,516.6859130859375],"flags":{},"order":8,"mode":0,"inputs":[{"name":"Multi_prompts","type":"STRING","widget":{"name":"Multi_prompts"},"link":307}],"outputs":[{"localized_name":"prompt","name":"prompt","shape":6,"type":"STRING","slot_index":0,"links":[138]},{"localized_name":"prompt_debug","name":"prompt_debug","shape":6,"type":"STRING","slot_index":1,"links":[198]}],"properties":{"cnr_id":"comfyui_creaprompt","ver":"9e8a245c41308383af70202af5fcca3a08eb56ea","Node name for S&R":"CreaPrompt List"},"widgets_values":["A hyper-realistic, high-contrast surreal close-up of a human face with a cracked marble texture, as if it were a gray marble sculpture. The smooth, cool gray tones of the marble surface create a striking contrast against the intricate, glowing cracks that spread across the polished exterior, emitting a soft, ethereal light. From the glowing fissures, delicate beams of light radiate outward, piercing through the surface and illuminating the surrounding area with a mystical glow. The face appears fragmented yet beautifully serene, with closed eyes and slightly parted lips, conveying an aura of fragility and mystery. The lighting is soft and diffused, accentuating the glossy, reflective quality of the gray marble while casting gentle shadows that highlight the depth and complexity of the glowing fissures. The light rays streaming from the cracks interact subtly with the surrounding environment, adding depth and a sense of movement. The overall color palette consists of cool gray tones, radiant light beams, and glowing fissures, evoking a dreamlike and otherworldly atmosphere. Fine marble veins subtly run through the surface, enhancing the natural elegance and timeless quality of the piece","",""]},{"id":57,"type":"ttN textDebug","pos":[-131.14041137695312,861.4549560546875],"size":[503.48687744140625,438.7097473144531],"flags":{},"order":11,"mode":0,"inputs":[{"name":"text","type":"STRING","widget":{"name":"text"},"link":198}],"outputs":[{"localized_name":"text","name":"text","type":"STRING","links":null}],"properties":{"cnr_id":"comfyui_tinyterranodes","ver":"c669e6cff81ba44cce91c9eee3236c1a64725394","Node name for S&R":"ttN textDebug","ttNnodeVersion":"1.0."},"widgets_values":[false,"","Always","","➡️dressed in a sophisticated blazer paired with a silk slip dress and heels,Ilford XP2 400,side lit,Hagia Sophia,Bleached spikes,Overdetailed art Best quality ultra sharp intricate details Fine art,Brown hair"]},{"id":61,"type":"PreviewImage","pos":[1066.86376953125,65.42341613769531],"size":[1168.1070556640625,1150.4288330078125],"flags":{},"order":16,"mode":0,"inputs":[{"localized_name":"images","name":"images","type":"IMAGE","link":233}],"outputs":[],"properties":{"cnr_id":"comfy-core","ver":"0.3.27","Node name for S&R":"PreviewImage"},"widgets_values":[]},{"id":47,"type":"CreaPrompt","pos":[-486.2265930175781,87.68507385253906],"size":[315,1158],"flags":{},"order":6,"mode":0,"inputs":[],"outputs":[{"localized_name":"prompt","name":"prompt","shape":3,"type":"STRING","slot_index":0,"links":[307]},{"localized_name":"seed","name":"seed","shape":3,"type":"INT","links":null}],"properties":{"cnr_id":"comfyui_creaprompt","ver":"9e8a245c41308383af70202af5fcca3a08eb56ea","Node name for S&R":"CreaPrompt"},"widgets_values":["🎲random","disabled","disabled","disabled","disabled","🎲random","disabled","disabled","disabled","disabled","disabled","disabled","disabled","🎲random","disabled","disabled","disabled","🎲random","disabled","disabled","disabled","disabled","disabled","disabled","disabled","disabled","disabled","disabled","disabled","🎲random","disabled","disabled","🎲random","disabled","disabled","disabled","disabled","disabled","🎲random","disabled","disabled","disabled",1,"disabled",198318694248,"randomize"]},{"id":111,"type":"FluxKeyModifier","pos":[714.8130493164062,239.8975830078125],"size":[332.036865234375,486],"flags":{},"order":7,"mode":0,"inputs":[{"localized_name":"unet_model","name":"unet_model","type":"MODEL","link":331}],"outputs":[{"localized_name":"model","name":"model","type":"MODEL","links":[332,333]},{"localized_name":"random_values","name":"random_values","type":"STRING","links":null}],"properties":{"Node name for S&R":"FluxKeyModifier"},"widgets_values":[true,false,false,"Flux_keys_modified.safetensors",0,false,0,false,0,false,0,false,0,false,0,false,0,false]}],"links":[[12,10,0,8,1,"VAE"],[19,16,0,13,2,"SAMPLER"],[20,17,0,13,3,"SIGMAS"],[24,13,0,8,0,"LATENT"],[30,22,0,13,1,"GUIDER"],[37,25,0,13,0,"NOISE"],[41,6,0,26,0,"CONDITIONING"],[42,26,0,22,1,"CONDITIONING"],[116,27,0,13,4,"LATENT"],[138,48,0,6,1,"STRING"],[198,48,1,57,0,"STRING"],[230,11,0,6,0,"CLIP"],[233,8,0,61,0,"IMAGE"],[307,47,0,48,0,"STRING"],[331,12,0,111,0,"MODEL"],[332,111,0,22,0,"MODEL"],[333,111,0,17,0,"MODEL"]],"groups":[],"config":{},"extra":{"ds":{"scale":0.6830134553650705,"offset":[391.1040341605847,89.1044530176494]},"groupNodes":{},"ue_links":[],"node_versions":{"comfy-core":"0.3.13","ComfyUI_tinyterraNodes":"339ee9c183d6fed5e90fa46c1e7fddc4d6efdbd2"}},"version":0.4}